sql_fixture/__init__.py
sql_fixture/fixture.py
sql_fixture/logger.py
sql_fixture/py.typed
sql_fixture-0.1.0.dist-info/METADATA
sql_fixture-0.1.0.dist-info/WHEEL
sql_fixture-0.1.0.dist-info/licenses/LICENSE
sql_fixture-0.1.0.dist-info/RECORD
