Metadata-Version: 2.1
Name: sql_fixture
Version: 0.1.0
Summary: Load YAML data fixtures for SQLAlchemy ✨
Project-URL: Homepage, https://github.com/yezz123/sql-fixture
Project-URL: Funding, https://github.com/sponsors/yezz123
Author-email: Yasser Tahiri <hello@yezz.me>
License-Expression: MIT
License-File: LICENSE
Classifier: Intended Audience :: Developers
Classifier: License :: OSI Approved :: MIT License
Classifier: Operating System :: OS Independent
Classifier: Programming Language :: Python
Classifier: Programming Language :: Python :: 3 :: Only
Classifier: Programming Language :: Python :: 3.7
Classifier: Programming Language :: Python :: 3.8
Classifier: Programming Language :: Python :: 3.9
Classifier: Programming Language :: Python :: 3.10
Classifier: Programming Language :: Python :: 3.11
Classifier: Topic :: Database
Classifier: Typing :: Typed
Requires-Python: >=3.7
Requires-Dist: colorama
Requires-Dist: pyyaml
Requires-Dist: sqlalchemy<2.1.0,>=1.3.18
Requires-Dist: typing-extensions<4.6.0,>=3.7.4
Provides-Extra: lint
Requires-Dist: mypy==1.0.1; extra == 'lint'
Requires-Dist: pre-commit==3.1.0; extra == 'lint'
Provides-Extra: test
Requires-Dist: codecov==2.1.12; extra == 'test'
Requires-Dist: pytest-asyncio==0.20.3; extra == 'test'
Requires-Dist: pytest-cov==4.0.0; extra == 'test'
Requires-Dist: pytest-pretty; extra == 'test'
Requires-Dist: pytest==7.2.1; extra == 'test'
